LICENSE
click_sources/__init__.py
click_sources/exceptions.py
click_sources/impl/__init__.py
click_sources/impl/ini_source.py
click_sources/impl/json_source.py
click_sources/impl/toml_source.py
click_sources/impl/yaml_source.py
click_sources/options.py
click_sources/source.py
click_sources-0.1.0a1.dist-info/LICENSE
click_sources-0.1.0a1.dist-info/WHEEL
click_sources-0.1.0a1.dist-info/METADATA
click_sources-0.1.0a1.dist-info/RECORD
